predictably/__init__.py
predictably/base/__init__.py
predictably/base/_base.py
predictably/statistical_tests/__init__.py
predictably/univariate/__init__.py
predictably/utilities/__init__.py
predictably/utilities/transformations.py
predictably/utilities/validations.py
predictably-0.1.4.dist-info/LICENSE
predictably-0.1.4.dist-info/METADATA
predictably-0.1.4.dist-info/WHEEL
predictably-0.1.4.dist-info/top_level.txt
predictably-0.1.4.dist-info/RECORD
