Metadata-Version: 2.1
Name: predictably
Version: 0.1.4
Summary: Scikit-learn compatible Python forecasting module
Home-page: https://rnkuhns.github.io/predict-ably/
Author: Ryan Kuhns
Author-email: rnkuhns@gmail.com
License: BSD-3
Platform: UNKNOWN
Classifier: Programming Language :: Python :: 3
Classifier: Development Status :: 1 - Planning
Requires-Dist: numpy (>=1.13.3)
Requires-Dist: scipy
Requires-Dist: statsmodels (>=0.10)
Requires-Dist: scikit-learn
Provides-Extra: dev
Requires-Dist: pip-tools ; extra == 'dev'
Requires-Dist: rpy2 ; extra == 'dev'
